paude/__init__.py
paude/__main__.py
paude/cli.py
paude/domains.py
paude/dry_run.py
paude/environment.py
paude/git_remote.py
paude/hash.py
paude/mounts.py
paude/platform.py
paude/utils.py
paude/venv.py
paude/backends/__init__.py
paude/backends/base.py
paude/backends/podman.py
paude/backends/openshift/__init__.py
paude/backends/openshift/backend.py
paude/backends/openshift/build.py
paude/backends/openshift/config.py
paude/backends/openshift/exceptions.py
paude/backends/openshift/oc.py
paude/backends/openshift/proxy.py
paude/backends/openshift/resources.py
paude/backends/openshift/sync.py
paude/config/__init__.py
paude/config/claude_layer.py
paude/config/detector.py
paude/config/dockerfile.py
paude/config/models.py
paude/config/parser.py
paude/container/__init__.py
paude/container/image.py
paude/container/network.py
paude/container/podman.py
paude/container/runner.py
paude/features/__init__.py
paude/features/downloader.py
paude/features/installer.py
paude-0.6.0.dist-info/METADATA
paude-0.6.0.dist-info/WHEEL
paude-0.6.0.dist-info/entry_points.txt
paude-0.6.0.dist-info/licenses/LICENSE
paude-0.6.0.dist-info/RECORD
